{"id":50393,"date":"2026-04-02T05:54:47","date_gmt":"2026-04-02T04:54:47","guid":{"rendered":"https:\/\/www.portugalrunning.com\/?post_type=ajde_events&#038;p=50393"},"modified":"2026-04-02T06:01:45","modified_gmt":"2026-04-02T05:01:45","slug":"meia-maratona-avieiros","status":"publish","type":"ajde_events","link":"https:\/\/www.portugalrunning.com\/eventos\/meia-maratona-avieiros\/","title":{"rendered":"Meia Maratona Avieiros 2026"},"content":{"rendered":"\n<p>As <strong>inscri\u00e7\u00f5es para a Meia Maratona Avieiros 2026<\/strong> abrem no dia 5 de abril, convidando os corredores a explorar as margens do Tejo numa experi\u00eancia que une desporto e patrim\u00f3nio. Organizada pelo S\u00f3Rio em parceria com os Scalabis Night Runners, esta <strong>corrida em Santar\u00e9m<\/strong> destaca-se pelo contacto direto com a cultura avieira. O evento foca-se na promo\u00e7\u00e3o da identidade ribeirinha atrav\u00e9s de um percurso que acompanha a serenidade das \u00e1guas do rio.<\/p>\n\n\n\n<p>\ud83d\udccb <strong>Dados T\u00e9cnicos<\/strong><\/p>\n\n\n\n<ul class=\"wp-block-list\">\n<li><strong>Nome:<\/strong> Meia Maratona Avieiros 2026<\/li>\n\n\n\n<li><strong>Data:<\/strong> 10 de junho de 2026 (Feriado Nacional)<\/li>\n\n\n\n<li><strong>Local:<\/strong> Santar\u00e9m (Zona Ribeirinha \/ Caneiras)<\/li>\n\n\n\n<li><strong>Terreno\/Dist\u00e2ncias:<\/strong> Percurso maioritariamente plano junto ao rio. Inclui Meia Maratona (21 km), Desafio do Tejo (10 km) e Caminhada (10 km).<\/li>\n<\/ul>\n\n\n\n<p>\u2b50 <strong>Diferenciador<\/strong> O evento celebra a Cultura Avieira, classificada como Patrim\u00f3nio Imaterial Nacional. Os atletas percorrem caminhos que ligam as antigas aldeias de pescadores (palafitas), proporcionando uma imers\u00e3o cultural \u00fanica onde o rio Tejo \u00e9 o protagonista absoluto de cada quil\u00f3metro percorrido.<\/p>\n\n\n\n<p>\ud83c\udf0d <strong>Sobre o Local<\/strong> Santar\u00e9m, a &#8220;Capital do G\u00f3tico&#8221;, ergue-se sobre o planalto ribeirinho, oferecendo uma das vistas mais amplas sobre a lez\u00edria. Ap\u00f3s cruzar a meta junto ao rio, a <strong>Sopa de Peixe do Rio<\/strong> ou o <strong>Ensopado de Enguias<\/strong> surgem como as sugest\u00f5es gastron\u00f3micas ideais para recuperar for\u00e7as, honrando a tradi\u00e7\u00e3o culin\u00e1ria dos pescadores avieiros.<\/p>\n\n\n\n<p><\/p>\n","protected":false},"author":1,"featured_media":50400,"menu_order":0,"comment_status":"closed","ping_status":"closed","template":"","meta":{"zakra_general_container_width":0,"zakra_general_content_width":0,"zakra_general_sidebar_width":0,"zakra_sticky_header":"customizer","zakra_header_main_area":true,"zakra_site_logo_width":0,"zakra_header_top_enabled":"customizer","zakra_header_top_style":"customizer","zakra_primary_menu_item_style":"customizer","zakra_page_header_text_color":"","zakra_page_header_layout":"customizer","zakra_page_title_bg":"","zakra_footer_widgets_bg_image":0,"zakra_page_title_bg_repeat":"customizer","zakra_page_title_bg_position":"customizer","zakra_page_title_bg_size":"customizer","zakra_page_title_bg_attachment":"customizer","zakra_breadcrumbs_enabled":"customizer","zakra_breadcrumbs_text_color":"","zakra_breadcrumbs_separator_color":"","zakra_breadcrumbs_link_color":"","zakra_breadcrumbs_link_hover_color":"","zakra_page_title_bg_image":0,"zakra_footer_widgets_enabled":"customizer","zakra_footer_column_layout_1_style":"customizer","zakra_footer_widgets_bg":"","zakra_footer_widgets_bg_repeat":"customizer","zakra_footer_widgets_bg_position":"customizer","zakra_footer_widgets_bg_size":"customizer","zakra_footer_widgets_bg_attachment":"customizer","zakra_footer_bar_enabled":"customizer","zakra_footer_bar_style":"customizer","zakra_page_container_layout":"customizer","zakra_page_sidebar_layout":"customizer","zakra_remove_content_margin":false,"zakra_sidebar":"customizer","zakra_transparent_header":"customizer","zakra_logo":0,"zakra_main_header_style":"default","zakra_menu_item_color":"","zakra_menu_item_hover_color":"","zakra_menu_item_active_color":"","zakra_menu_active_style":"","zakra_page_header":true},"tags":[],"event_type":[672,27,28,41],"event_type_2":[727,820,39],"event_type_3":[],"event_type_4":[],"event_type_5":[],"class_list":["post-50393","ajde_events","type-ajde_events","status-publish","has-post-thumbnail","hentry","event_location-santarem","event_type-caminhada","event_type-corrida","event_type-corrida-10-km","event_type-meiamaratona","event_type_2-lisboa-e-centro","event_type_2-portugal","event_type_2-santarem"],"featured_image_src":"https:\/\/www.portugalrunning.com\/wp-content\/uploads\/2026\/04\/banner-meia-maratona-avieiros-2026-min.jpg","ams_acf":[],"_links":{"self":[{"href":"https:\/\/www.portugalrunning.com\/wp-json\/wp\/v2\/ajde_events\/50393","targetHints":{"allow":["GET"]}}],"collection":[{"href":"https:\/\/www.portugalrunning.com\/wp-json\/wp\/v2\/ajde_events"}],"about":[{"href":"https:\/\/www.portugalrunning.com\/wp-json\/wp\/v2\/types\/ajde_events"}],"author":[{"embeddable":true,"href":"https:\/\/www.portugalrunning.com\/wp-json\/wp\/v2\/users\/1"}],"replies":[{"embeddable":true,"href":"https:\/\/www.portugalrunning.com\/wp-json\/wp\/v2\/comments?post=50393"}],"version-history":[{"count":1,"href":"https:\/\/www.portugalrunning.com\/wp-json\/wp\/v2\/ajde_events\/50393\/revisions"}],"predecessor-version":[{"id":50394,"href":"https:\/\/www.portugalrunning.com\/wp-json\/wp\/v2\/ajde_events\/50393\/revisions\/50394"}],"wp:featuredmedia":[{"embeddable":true,"href":"https:\/\/www.portugalrunning.com\/wp-json\/wp\/v2\/media\/50400"}],"wp:attachment":[{"href":"https:\/\/www.portugalrunning.com\/wp-json\/wp\/v2\/media?parent=50393"}],"wp:term":[{"taxonomy":"post_tag","embeddable":true,"href":"https:\/\/www.portugalrunning.com\/wp-json\/wp\/v2\/tags?post=50393"},{"taxonomy":"event_type","embeddable":true,"href":"https:\/\/www.portugalrunning.com\/wp-json\/wp\/v2\/event_type?post=50393"},{"taxonomy":"event_type_2","embeddable":true,"href":"https:\/\/www.portugalrunning.com\/wp-json\/wp\/v2\/event_type_2?post=50393"},{"taxonomy":"event_type_3","embeddable":true,"href":"https:\/\/www.portugalrunning.com\/wp-json\/wp\/v2\/event_type_3?post=50393"},{"taxonomy":"event_type_4","embeddable":true,"href":"https:\/\/www.portugalrunning.com\/wp-json\/wp\/v2\/event_type_4?post=50393"},{"taxonomy":"event_type_5","embeddable":true,"href":"https:\/\/www.portugalrunning.com\/wp-json\/wp\/v2\/event_type_5?post=50393"}],"curies":[{"name":"wp","href":"https:\/\/api.w.org\/{rel}","templated":true}]}}