{"id":794,"date":"2019-12-24T15:26:22","date_gmt":"2019-12-24T15:26:22","guid":{"rendered":"https:\/\/www.portugalrunning.com\/portugalrunning\/?post_type=ajde_events&#038;p=794"},"modified":"2020-01-05T15:29:31","modified_gmt":"2020-01-05T15:29:31","slug":"almada-trail","status":"publish","type":"ajde_events","link":"https:\/\/www.portugalrunning.com\/eventos\/almada-trail\/","title":{"rendered":"Almada Trail 2020"},"content":{"rendered":"<p>O CPA &#8211; Clube Pra\u00e7as da Armada com o apoio t\u00e9cnico da Werun e a co-parceria da C\u00e2mara Municipal de Almada, ir\u00e3o organizar o 3\u00ba Almada Trail, na cidade de Almada, com Partida e Chegada no Parque Desportivo do Atl\u00e2ntico Costa da Caparica.<\/p>\n<p>&nbsp;<\/p>\n<p><strong>Programa \/ Hor\u00e1rio<\/strong><\/p>\n<p>9h00 &#8211; Corrida Pais &amp; Filhos<br \/>\n9h30 &#8211; Partida Trail Longo K25+<br \/>\n10h00 &#8211; Partida K15+<br \/>\n10h05 &#8211; Partida Caminhada<br \/>\n11h15 &#8211; Previs\u00e3o de chegada dos primeiros atletas K15+<br \/>\n11h30 &#8211; Previs\u00e3o de chegada dos primeiros atletas K25+<br \/>\n12h00 &#8211; Entrega prevista dos trof\u00e9us<\/p>\n<p><strong>Tempo limite<\/strong><\/p>\n<ul>\n<li>Caminhada: 3h00<\/li>\n<li>Trail curto: 3h30<\/li>\n<li>Trail Longo: 4h00 (controlo de passagem: se chegar aos 10,5 km e o tempo for superior a\u00a01h40, ser\u00e1 convidado a\u00a0fazer o restante percurso do Trail Curto)<\/li>\n<\/ul>\n<p><strong>Metodologia de controlo de tempos<\/strong><\/p>\n<p>O processo de controlo de tempos do atleta \u00e9 feito atrav\u00e9s de sistema electr\u00f3nico, por chip inclu\u00eddo no dorsal.<\/p>\n","protected":false},"author":1,"featured_media":795,"menu_order":0,"comment_status":"open","ping_status":"closed","template":"","meta":{"zakra_general_container_width":0,"zakra_general_content_width":0,"zakra_general_sidebar_width":0,"zakra_sticky_header":"customizer","zakra_header_main_area":true,"zakra_site_logo_width":0,"zakra_header_top_enabled":"customizer","zakra_header_top_style":"customizer","zakra_primary_menu_item_style":"customizer","zakra_page_header_text_color":"","zakra_page_header_layout":"customizer","zakra_page_title_bg":"","zakra_footer_widgets_bg_image":0,"zakra_page_title_bg_repeat":"customizer","zakra_page_title_bg_position":"customizer","zakra_page_title_bg_size":"customizer","zakra_page_title_bg_attachment":"customizer","zakra_breadcrumbs_enabled":"customizer","zakra_breadcrumbs_text_color":"","zakra_breadcrumbs_separator_color":"","zakra_breadcrumbs_link_color":"","zakra_breadcrumbs_link_hover_color":"","zakra_page_title_bg_image":0,"zakra_footer_widgets_enabled":"customizer","zakra_footer_column_layout_1_style":"customizer","zakra_footer_widgets_bg":"","zakra_footer_widgets_bg_repeat":"customizer","zakra_footer_widgets_bg_position":"customizer","zakra_footer_widgets_bg_size":"customizer","zakra_footer_widgets_bg_attachment":"customizer","zakra_footer_bar_enabled":"customizer","zakra_footer_bar_style":"customizer","zakra_sidebar_layout":"customizer","zakra_remove_content_margin":false,"zakra_sidebar":"customizer","zakra_transparent_header":"customizer","zakra_logo":0,"zakra_main_header_style":"default","zakra_menu_item_color":"","zakra_menu_item_hover_color":"","zakra_menu_item_active_color":"","zakra_menu_active_style":"","zakra_page_header":true},"tags":[],"event_type":[22],"event_type_2":[48],"event_type_3":[],"event_type_4":[],"event_type_5":[],"class_list":["post-794","ajde_events","type-ajde_events","status-publish","has-post-thumbnail","hentry","event_location-parque-desportivo-do-atlantico-costa-da-caparica","event_organizer-cpa","event_type-trail","event_type_2-setubal"],"featured_image_src":"https:\/\/www.portugalrunning.com\/wp-content\/uploads\/2019\/12\/1-17.jpg","ams_acf":[],"_links":{"self":[{"href":"https:\/\/www.portugalrunning.com\/wp-json\/wp\/v2\/ajde_events\/794","targetHints":{"allow":["GET"]}}],"collection":[{"href":"https:\/\/www.portugalrunning.com\/wp-json\/wp\/v2\/ajde_events"}],"about":[{"href":"https:\/\/www.portugalrunning.com\/wp-json\/wp\/v2\/types\/ajde_events"}],"author":[{"embeddable":true,"href":"https:\/\/www.portugalrunning.com\/wp-json\/wp\/v2\/users\/1"}],"replies":[{"embeddable":true,"href":"https:\/\/www.portugalrunning.com\/wp-json\/wp\/v2\/comments?post=794"}],"version-history":[{"count":0,"href":"https:\/\/www.portugalrunning.com\/wp-json\/wp\/v2\/ajde_events\/794\/revisions"}],"wp:featuredmedia":[{"embeddable":true,"href":"https:\/\/www.portugalrunning.com\/wp-json\/wp\/v2\/media\/795"}],"wp:attachment":[{"href":"https:\/\/www.portugalrunning.com\/wp-json\/wp\/v2\/media?parent=794"}],"wp:term":[{"taxonomy":"post_tag","embeddable":true,"href":"https:\/\/www.portugalrunning.com\/wp-json\/wp\/v2\/tags?post=794"},{"taxonomy":"event_type","embeddable":true,"href":"https:\/\/www.portugalrunning.com\/wp-json\/wp\/v2\/event_type?post=794"},{"taxonomy":"event_type_2","embeddable":true,"href":"https:\/\/www.portugalrunning.com\/wp-json\/wp\/v2\/event_type_2?post=794"},{"taxonomy":"event_type_3","embeddable":true,"href":"https:\/\/www.portugalrunning.com\/wp-json\/wp\/v2\/event_type_3?post=794"},{"taxonomy":"event_type_4","embeddable":true,"href":"https:\/\/www.portugalrunning.com\/wp-json\/wp\/v2\/event_type_4?post=794"},{"taxonomy":"event_type_5","embeddable":true,"href":"https:\/\/www.portugalrunning.com\/wp-json\/wp\/v2\/event_type_5?post=794"}],"curies":[{"name":"wp","href":"https:\/\/api.w.org\/{rel}","templated":true}]}}