{"id":2926,"date":"2021-06-03T19:25:31","date_gmt":"2021-06-03T19:25:31","guid":{"rendered":"https:\/\/www.portugalrunning.com\/?post_type=ajde_events&#038;p=2926"},"modified":"2021-06-03T19:25:32","modified_gmt":"2021-06-03T19:25:32","slug":"vimeiro-trail-run-2021","status":"publish","type":"ajde_events","link":"https:\/\/www.portugalrunning.com\/eventos\/vimeiro-trail-run-2021\/","title":{"rendered":"Vimeiro Trail Run 2021"},"content":{"rendered":"\n<p>O\u00a0\u00a0TURRES TRAIL\u00a0\u00a0CLUBE , com o apoio da Junta de Freguesia de A dos Cunhados e Maceira\u00a0\u00a0, Externato de Penafirme\u00a0\u00a0e \u00e1guas do VIMEIRO\u00a0\u00a0\u00a0vai realizar no pr\u00f3ximo dia 12 de Setembro de 2021, pelas 9:00 horas, a 6\u00ba edi\u00e7\u00e3o do evento denominado\u00a0&#8220;<strong>\u00a0\u00a0VIMEIRO TRAIL RUN 2021<\/strong>&#8220;. Este evento, ter\u00e1 um Trail Longo de Grau 2, um Trail Curto de Grau 2 e um Mini Trail \/ caminhada . O percurso do Trail Run \u00e9 circular. O local de partida e chegada assim como o secretariado e almo\u00e7o\u00a0\u00a0ser\u00e1\u00a0\u00a0no Externato de Penafirme\u00a0\u00a0.<br><strong>A edi\u00e7\u00e3o de 2021 na distancia de 30 km\u00a0\u00a0esta englobada no circuito nacional Trail ATRP serie 150 .<\/strong><\/p>\n","protected":false},"author":1,"featured_media":2927,"menu_order":0,"comment_status":"open","ping_status":"closed","template":"","meta":{"zakra_general_container_width":0,"zakra_general_content_width":0,"zakra_general_sidebar_width":0,"zakra_sticky_header":"customizer","zakra_header_main_area":true,"zakra_site_logo_width":0,"zakra_header_top_enabled":"customizer","zakra_header_top_style":"customizer","zakra_primary_menu_item_style":"customizer","zakra_page_header_text_color":"","zakra_page_header_layout":"customizer","zakra_page_title_bg":"","zakra_footer_widgets_bg_image":0,"zakra_page_title_bg_repeat":"customizer","zakra_page_title_bg_position":"customizer","zakra_page_title_bg_size":"customizer","zakra_page_title_bg_attachment":"customizer","zakra_breadcrumbs_enabled":"customizer","zakra_breadcrumbs_text_color":"","zakra_breadcrumbs_separator_color":"","zakra_breadcrumbs_link_color":"","zakra_breadcrumbs_link_hover_color":"","zakra_page_title_bg_image":0,"zakra_footer_widgets_enabled":"customizer","zakra_footer_column_layout_1_style":"customizer","zakra_footer_widgets_bg":"","zakra_footer_widgets_bg_repeat":"customizer","zakra_footer_widgets_bg_position":"customizer","zakra_footer_widgets_bg_size":"customizer","zakra_footer_widgets_bg_attachment":"customizer","zakra_footer_bar_enabled":"customizer","zakra_footer_bar_style":"customizer","zakra_sidebar_layout":"customizer","zakra_remove_content_margin":false,"zakra_sidebar":"customizer","zakra_transparent_header":"customizer","zakra_logo":0,"zakra_main_header_style":"default","zakra_menu_item_color":"","zakra_menu_item_hover_color":"","zakra_menu_item_active_color":"","zakra_menu_active_style":"","zakra_page_header":true},"tags":[],"event_type":[22],"event_type_2":[33],"event_type_3":[],"event_type_4":[],"event_type_5":[],"class_list":["post-2926","ajde_events","type-ajde_events","status-publish","has-post-thumbnail","hentry","event_location-penafirme-torres-vedras","event_type-trail","event_type_2-lisboa"],"featured_image_src":"https:\/\/www.portugalrunning.com\/wp-content\/uploads\/2021\/06\/194504195_2920445981553396_4025398887037155998_n-1024x575.jpg","ams_acf":[],"_links":{"self":[{"href":"https:\/\/www.portugalrunning.com\/wp-json\/wp\/v2\/ajde_events\/2926","targetHints":{"allow":["GET"]}}],"collection":[{"href":"https:\/\/www.portugalrunning.com\/wp-json\/wp\/v2\/ajde_events"}],"about":[{"href":"https:\/\/www.portugalrunning.com\/wp-json\/wp\/v2\/types\/ajde_events"}],"author":[{"embeddable":true,"href":"https:\/\/www.portugalrunning.com\/wp-json\/wp\/v2\/users\/1"}],"replies":[{"embeddable":true,"href":"https:\/\/www.portugalrunning.com\/wp-json\/wp\/v2\/comments?post=2926"}],"version-history":[{"count":0,"href":"https:\/\/www.portugalrunning.com\/wp-json\/wp\/v2\/ajde_events\/2926\/revisions"}],"wp:featuredmedia":[{"embeddable":true,"href":"https:\/\/www.portugalrunning.com\/wp-json\/wp\/v2\/media\/2927"}],"wp:attachment":[{"href":"https:\/\/www.portugalrunning.com\/wp-json\/wp\/v2\/media?parent=2926"}],"wp:term":[{"taxonomy":"post_tag","embeddable":true,"href":"https:\/\/www.portugalrunning.com\/wp-json\/wp\/v2\/tags?post=2926"},{"taxonomy":"event_type","embeddable":true,"href":"https:\/\/www.portugalrunning.com\/wp-json\/wp\/v2\/event_type?post=2926"},{"taxonomy":"event_type_2","embeddable":true,"href":"https:\/\/www.portugalrunning.com\/wp-json\/wp\/v2\/event_type_2?post=2926"},{"taxonomy":"event_type_3","embeddable":true,"href":"https:\/\/www.portugalrunning.com\/wp-json\/wp\/v2\/event_type_3?post=2926"},{"taxonomy":"event_type_4","embeddable":true,"href":"https:\/\/www.portugalrunning.com\/wp-json\/wp\/v2\/event_type_4?post=2926"},{"taxonomy":"event_type_5","embeddable":true,"href":"https:\/\/www.portugalrunning.com\/wp-json\/wp\/v2\/event_type_5?post=2926"}],"curies":[{"name":"wp","href":"https:\/\/api.w.org\/{rel}","templated":true}]}}